LICENSE.md
android_resources_checker/__init__.py
android_resources_checker/analyzer.py
android_resources_checker/app.py
android_resources_checker/entrypoint.py
android_resources_checker/files.py
android_resources_checker/models.py
android_resources_checker/reporting.py
android_resources_checker/resources.py
android_resources_checker/validator.py
android_resources_checker-0.0.10.dist-info/entry_points.txt
android_resources_checker-0.0.10.dist-info/LICENSE.md
android_resources_checker-0.0.10.dist-info/WHEEL
android_resources_checker-0.0.10.dist-info/METADATA
android_resources_checker-0.0.10.dist-info/RECORD
