Metadata-Version: 2.1
Name: android-resources-checker
Version: 0.0.10
Summary: Check if your android resources are being unused.
Home-page: https://github.com/fabiocarballo/android-resources-checker
License: MIT
Author: Fabio Carballo
Author-email: fabio.og.carballo@gmail.com
Requires-Python: >=3.8,<4.0
Classifier: License :: OSI Approved :: MIT License
Classifier: Programming Language :: Python :: 3
Classifier: Programming Language :: Python :: 3.8
Classifier: Programming Language :: Python :: 3.9
Requires-Dist: click (>=7.1.2,<8.0.0)
Requires-Dist: rich (>=10.0.0,<11.0.0)
Project-URL: Repository, https://github.com/fabiocarballo/android-resources-checker
